pysmlight/__init__.py
pysmlight/_version.py
pysmlight/const.py
pysmlight/exceptions.py
pysmlight/models.py
pysmlight/payload.py
pysmlight/py.typed
pysmlight/sse.py
pysmlight/web.py
pysmlight-0.2.13.dist-info/METADATA
pysmlight-0.2.13.dist-info/WHEEL
pysmlight-0.2.13.dist-info/licenses/LICENSE
pysmlight-0.2.13.dist-info/RECORD
